PyScreenReader.pyd
src/stubs/__init__.pyi
src/stubs/screen_reader.pyi
src/stubs/virtual_widgets.pyi
pyscreenreader-1.0.0a1.dist-info/WHEEL
pyscreenreader-1.0.0a1.dist-info/METADATA
pyscreenreader-1.0.0a1.dist-info/RECORD
