Metadata-Version: 2.1
Name: PyScreenReader
Author: The PyScreenReader Team
Home-page: https://github.com/PyScreenReader/PyScreenReader
License: MIT
Summary: PyScreenReader is a cross-platform Python library that wraps native accessibility APIs to collect widget tree information on the screen.
Classifier: Operating System :: Microsoft :: Windows
Classifier: Operating System :: MacOS
Classifier: Operating System :: POSIX :: Linux
Classifier: Topic :: Desktop Environment :: Gnome
Classifier: Development Status :: 3 - Alpha
Classifier: Programming Language :: C++
Classifier: Topic :: Software Development :: Libraries :: Application Frameworks
Classifier: Topic :: Software Development :: Libraries
Classifier: Typing :: Typed
Classifier: Topic :: Utilities
Classifier: License :: OSI Approved :: MIT License
Version: 1.0.0a1
